xecm/CSRestAPI.py
xecm/__init__.py
xecm-25.3.1.dist-info/licenses/LICENSE
xecm-25.3.1.dist-info/METADATA
xecm-25.3.1.dist-info/WHEEL
xecm-25.3.1.dist-info/top_level.txt
xecm-25.3.1.dist-info/RECORD
