Metadata-Version: 2.4
Name: xecm
Version: 25.3.1
Summary: Simple Python library to call Opentext Extended ECM REST API
Author-email: Philipp Egger <philipp.egger@handel-it.com>
License-Expression: MIT
Project-URL: Homepage, https://github.com/fitschgo/xecm
Project-URL: Issues, https://github.com/fitschgo/xecm/issues
Keywords: xecm,opentext,extendedecm,contentserver,otcs,otds
Classifier: Development Status :: 5 - Production/Stable
Classifier: Programming Language :: Python :: 3
Classifier: Operating System :: OS Independent
Classifier: Intended Audience :: Developers
Classifier: Topic :: Internet :: WWW/HTTP :: Dynamic Content :: Content Management System
Requires-Python: >=3.10
License-File: LICENSE
Requires-Dist: requests<3
Dynamic: license-file
